{
    "$schema": "https://schema.management.azure.com/schemas/2019-04-01/deploymentParameters.json#",
    "contentVersion": "1.0.0.0",
    "parameters": {
        "environmentType": {
            "value": "uat"
        },
        "postgreSQLServerName": {
            "value": "chiaradigi-dbsrv-uat"
        },
        "postgreSQLDatabaseName": {
            "value": "chiaradigi-db-uat"
        },
        "appServicePlanName": {
            "value": "chiaradigi-asp-uat"
        },
        "appServiceAPIAppName": {
            "value": "chiaradigi-be-uat"
        },
        "appServiceAppName": {
            "value": "chiaradigi-fe-uat"
        },
        "azureMonitorName": {
            "value": "chiaradigi-am"
        },
        "appInsightsName": {
            "value": "chiaradigi-ai"
        },
        "location": {
            "value": "Brazil South"
        },
        "postgreSQLSkuName": {
            "value": "Standard_B1ms"
        },
        "appServicePlanSkuName": {
            "value": "B1"
        }
    }
}